README.md
setup.py
dataclient/__init__.py
dataclient/cached_property.py
dataclient/client.py
dataclient/data.capnp
dataclient/mdal_pb2.py
dataclient/mdal_pb2_grpc.py
dataclient/result.py
dataclient.egg-info/PKG-INFO
dataclient.egg-info/SOURCES.txt
dataclient.egg-info/dependency_links.txt
dataclient.egg-info/not-zip-safe
dataclient.egg-info/top_level.txt