Metadata-Version: 1.0
Name: dataclient
Version: 0.1.10
Summary: MDAL client v2
Home-page: UNKNOWN
Author: UNKNOWN
Author-email: UNKNOWN
License: UNKNOWN
Platform: UNKNOWN
